elsdk/__init__.py
elsdk/events.py
elsdk/infra.py
elsdk/invite.py
elsdk/session.py
elsdk/state.py
elsdk/utils/__init__.py
elsdk/utils/common.py
elsdk/utils/exceptions.py
elsdk/utils/log.py
elsdk-0.1.2.dist-info/METADATA
elsdk-0.1.2.dist-info/WHEEL
elsdk-0.1.2.dist-info/top_level.txt
elsdk-0.1.2.dist-info/RECORD
