Metadata-Version: 2.1
Name: elsdk
Version: 0.1.2
Summary: SDK for Scheduling and Managing EL Platform
Home-page: https://einstonlabs.com
Author: EinstonLabs
Author-email: info@einstonlabs.com
License: All Rights Reserved by Einston Labs
Project-URL: Documentation, https://docs.einstonlabs.com
Keywords: elp,einston,sdk
Requires-Python: ~=3.8
Requires-Dist: requests (==2.31.0)
Requires-Dist: pycryptodome (==3.18.0)
Requires-Dist: PyJWT (==2.7.0)
Requires-Dist: python-dateutil (==2.8.2)
Requires-Dist: python-json-logger (==2.0.7)
